alfreds-0.0.19.data/scripts/alfreds
alfreds-0.0.19.data/scripts/main.py
alfreds_init/__init__.py
alfreds_init/init.py
alfreds_seed/__init__.py
alfreds_seed/seed.py
alfreds_start/__init__.py
alfreds_start/start.py
alfreds_stop/__init__.py
alfreds_stop/stop.py
alfreds_update/__init__.py
alfreds_update/update_agent.py
alfreds_update/update_working_directory.py
refresh/__init__.py
refresh/refresh.py
alfreds-0.0.19.dist-info/METADATA
alfreds-0.0.19.dist-info/WHEEL
alfreds-0.0.19.dist-info/top_level.txt
alfreds-0.0.19.dist-info/RECORD
