Metadata-Version: 2.1
Name: alfreds
Version: 0.0.19
Summary: Alfreds CLI
Home-page: https://github.com/TBD
Author: Data Facade
Author-email: info@data-facade.com
Classifier: Programming Language :: Python
Classifier: Operating System :: MacOS :: MacOS X
Requires-Python: >=3.8
Requires-Dist: setuptools
Requires-Dist: wheel
Requires-Dist: tqdm
Requires-Dist: twine
Requires-Dist: requests
Requires-Dist: pyYAML
